setuptools_hacks/bypass_summary_newline.py
setuptools_hacks.bypass_summary_newline-1.0.0.dist-info/LICENSE
setuptools_hacks.bypass_summary_newline-1.0.0.dist-info/METADATA
setuptools_hacks.bypass_summary_newline-1.0.0.dist-info/WHEEL
setuptools_hacks.bypass_summary_newline-1.0.0.dist-info/entry_points.txt
setuptools_hacks.bypass_summary_newline-1.0.0.dist-info/top_level.txt
setuptools_hacks.bypass_summary_newline-1.0.0.dist-info/RECORD
